ocf_cli/__init__.py
ocf_cli/bin/__init__.py
ocf_cli/bin/ocf.py
ocf_cli/lib/core/config.py
ocf_cli/lib/pprint/_base.py
ocf_cli/lib/pprint/nodes.py
ocf_cli/lib/pprint/service.py
ocf_cli-0.0.2.dist-info/METADATA
ocf_cli-0.0.2.dist-info/WHEEL
ocf_cli-0.0.2.dist-info/entry_points.txt
ocf_cli-0.0.2.dist-info/top_level.txt
ocf_cli-0.0.2.dist-info/RECORD
