Metadata-Version: 2.1
Name: ocf-cli
Version: 0.0.2
Summary: OCF CLI
Author-email: Xiaozhe Yao <askxzyao@gmail.com>
Project-URL: Homepage, https://github.com/autoai-org/ocf
Project-URL: Bug Tracker, https://github.com/autoai-org/ocf/issues
Classifier: Programming Language :: Python :: 3
Classifier: License :: OSI Approved :: MIT License
Classifier: Operating System :: OS Independent
Requires-Python: >=3.7
Requires-Dist: typer
Requires-Dist: requests
Requires-Dist: rich
Requires-Dist: loguru
Requires-Dist: huggingface-hub
Requires-Dist: pynvml
